uptodateai/__init__.py
uptodateai/crawler.py
uptodateai/pipeline.py
uptodateai/utils.py
uptodateai-0.1.0.dist-info/LICENSE
uptodateai-0.1.0.dist-info/METADATA
uptodateai-0.1.0.dist-info/WHEEL
uptodateai-0.1.0.dist-info/top_level.txt
uptodateai-0.1.0.dist-info/RECORD
