Metadata-Version: 2.1
Name: uptodateai
Version: 0.1.0
Summary: A package for crawling and converting web content to Markdown
Home-page: https://github.com/yourusername/uptodateai
Author: Your Name
Author-email: your.email@example.com
Classifier: Development Status :: 3 - Alpha
Classifier: Intended Audience :: Developers
Classifier: License :: OSI Approved :: MIT License
Classifier: Operating System :: OS Independent
Classifier: Programming Language :: Python :: 3
Classifier: Programming Language :: Python :: 3.7
Classifier: Programming Language :: Python :: 3.8
Classifier: Programming Language :: Python :: 3.9
Requires-Python: >=3.7
License-File: LICENSE
Requires-Dist: scrapy
Requires-Dist: newspaper3k
Requires-Dist: markdown
Requires-Dist: beautifulsoup4
Requires-Dist: html2text
Requires-Dist: python-slugify
